{
	"id": "iNbF4l22xWv3a0U",
	"json": "{\"id\":\"iNbF4l22xWv3a0U\",\"url\":\"https://unienrol.com/scholarships/london-metropolitan-university\",\"uniqueKey\":\"https://unienrol.com/scholarships/london-metropolitan-university\",\"method\":\"GET\",\"noRetry\":false,\"retryCount\":0,\"errorMessages\":[],\"headers\":{},\"userData\":{\"label\":\"scholarship_overview\",\"__crawlee\":{\"skipNavigation\":false}}}",
	"method": "GET",
	"orderNo": 1694262964763,
	"retryCount": 0,
	"uniqueKey": "https://unienrol.com/scholarships/london-metropolitan-university",
	"url": "https://unienrol.com/scholarships/london-metropolitan-university"
}